qclib/PlatformQC.py
qclib/Platforms.py
qclib/QC.py
qclib/QCTests.py
qclib/__init__.py
qclib/__version__.py
qclib/utils/Thresholds.py
qclib/utils/__init__.py
qclib/utils/measurement.py
qclib/utils/navigation.py
qclib/utils/qc_input.py
qclib/utils/qc_input_helpers.py
qclib/utils/qctests_helpers.py
qclib/utils/validate_input.py
nivacloud_qclib-7.1.2.dist-info/LICENCE.md
nivacloud_qclib-7.1.2.dist-info/METADATA
nivacloud_qclib-7.1.2.dist-info/WHEEL
nivacloud_qclib-7.1.2.dist-info/top_level.txt
nivacloud_qclib-7.1.2.dist-info/RECORD
