Metadata-Version: 2.1
Name: nivacloud-qclib
Version: 7.1.2
Summary: Module containing QC tests
Home-page: https://github.com/NIVANorge/qclib
Author: Pierre Jaccard, Elizaveta Protsenko, Zofia Rudjord
Author-email: pja@niva.no, elizaveta.protsenko@niva.no, zofia.rudjord@niva.no
License: Owned by NIVA
Keywords: data quality tests
Platform: UNKNOWN
Classifier: Development Status :: 4 - Beta
Classifier: Intended Audience :: Developers
Classifier: License :: OSI Approved :: MIT License
Classifier: Programming Language :: Python :: 3
License-File: LICENCE.md
Requires-Dist: pandas (<2.0,>=1.1)
Requires-Dist: numpy (<2.0,>=1.16)
Requires-Dist: pydantic (<2.0,>=1.0)
Requires-Dist: matplotlib (<4.0,>=3.0)
Provides-Extra: test
Requires-Dist: pytest ; extra == 'test'
